Gestao_Imoveis/__init__.py
Gestao_Imoveis/gestão_de_imóveis.py
gestao_imoveis-0.1.0.dist-info/licenses/LICENSE.txt
gestao_imoveis-0.1.0.dist-info/METADATA
gestao_imoveis-0.1.0.dist-info/WHEEL
gestao_imoveis-0.1.0.dist-info/top_level.txt
gestao_imoveis-0.1.0.dist-info/RECORD
