Metadata-Version: 2.4
Name: gestao_imoveis
Version: 0.1.0
Summary: Ferramenta para gestão de imóveis
Home-page: https://github.com/silvagui04/GestaoImoveis/blob/main/Gestão_de_Imóveis.ipynb
Author: Guilherme Silva, Gonçalo Tavares, João Maia, Vasco Azevedo
Author-email: seu@email.com
License-File: LICENSE.txt
Dynamic: author
Dynamic: author-email
Dynamic: description
Dynamic: description-content-type
Dynamic: home-page
Dynamic: license-file
Dynamic: summary
